{
  "id": "weapon_general_types",
  "name": "Weapon general types",
  "types": [
    {
      "id": "simple_melee",
      "name": "Simple Melee"
    },
    {
      "id": "simple_ranged",
      "name": "Simple Ranged"
    },
    {
      "id": "martial_melee",
      "name": "Martial Melee"
    },
    {
      "id": "martial_ranged",
      "name": "Martial Ranged"
    },
    {
      "id": "simple_firearms",
      "name": "Simple Firearms"
    },
    {
      "id": "martial_firearms",
      "name": "Martial Firearms"
    },
    {
      "id": "simple_crossbows",
      "name": "Simple Crossbows"
    },
    {
      "id": "martial_crossbows",
      "name": "Martial Crossbows"
    }
  ]
}