{
  "resource_id": "archetype",
  "stats": {
    "id": "archetype_inerrant_voice_oracle_archetype__crb_",
    "name": {
      "value": "Inerrant Voice"
    },
    "source": {
      "value": "heroes_of_the_high_court"
    },
    "category": {
      "value": "archetype"
    },
    "prerequisites_text": {
      "value": ""
    },
    "description": {
      "value": "Bonus Spells Revelations An inerrant voice serves as a spiritual advisor to either a monarch or noble. Recommended Mysteries: Ancestor, intrigue, life, lore. Bonus Spells An inerrant voice gains the following bonus spells: shield other (2nd), augury (4th), divination (8th), vision (14th). These replace the bonus spells at those levels gained from the oracle\u00e2\u0080\u0099s mystery. Revelations An inerrant voice must take the following revelation at 3rd level. Vigilant Protector (Su) Each day when you recover your spells, you can select a specific person you know other than yourself as your ward. When your ward becomes the target of an attack or spell and you are aware of the attack, you can cast an abjuration spell you know on the ally as an immediate action. You must expend the appropriate spell slot and be able to target the ally as normal for the spell. At 11th level, as an immediate action when you know your ward is targeted, you can transpose yourself with your ward, teleporting into the original target\u00e2\u0080\u0099s square (and becoming the new target of the attack or spell) while your ally is teleported into yours; this is a teleportation effect that doesn\u00e2\u0080\u0099t provoke attacks of opportunity. You can use this revelation once per day, plus an additional time at 7th level and every 4 oracle levels thereafter."
    },
    "related_mechanical_resource_id": {
      "value": ""
    }
  }
}