{
  "resource_id": "archetype",
  "stats": {
    "id": "archetype_animal_and_terrain_domains__crb_",
    "name": {
      "value": "Animal and Terrain Domains"
    },
    "source": {
      "value": "um"
    },
    "category": {
      "value": "archetype"
    },
    "prerequisites_text": {
      "value": ""
    },
    "description": {
      "value": "Subpages Aquatic Domain Arctic Domain Badlands Domain Cave Domain Crocodile Domain Desert Domain Eagle Domain Frog Domain Jungle Domain Monkey Domain Mountain Domain Panther Domain Plains Domain Plane Of Air Domain Plane Of Earth Domain Plane Of Fire Domain Plane Of Water Domain Serpent Domain Swamp Domain Vulture Domain Wolf Domain Druids are devotees of nature, protecting the bleakest deserts and most verdant forests. Through their kinship with animals and the elements, they learn the most potent secrets the natural world has to offer, and can call upon great power in the form of both magical abilities like wild shape and a wide array of thematic spells. Whether tapping the fundamental magic of the elements or relying on the teeth and claws of wild creatures to accomplish their goals, druids are forces to be reckoned with, and those whose actions threaten the wild places these nature folk hold dear had best be prepared to suffer the consequences. Presented below are rules for animal and terrain domains—domains for druids whose focus is more specific than the Animal, Plant, Weather, or elemental domains. A druid with the nature’s bond ability can choose an animal domain or terrain domain listed here instead of one of the standard domains. Just like cleric domains, animal and terrain domains have granted powers and domain spells, and a druid who selects an animal or terrain domain gains a domain spell slot at each level. A druid who worships a deity (as opposed to nature in general) cannot select an animal or terrain domain that contradicts or is outside of the portfolio of her deity. If an animal or terrain domain ability calls for a saving throw, the DC of the save is equal to 10 + 1/2 the character’s druid level + her Wisdom modifier. Other nature-themed classes with access to domains may select an animal or terrain domain in place of a regular domain. ECOLOGY"
    },
    "related_mechanical_resource_id": {
      "value": "class_druid__crb_"
    }
  }
}