{
  "resource_id": "deity",
  "stats": {
    "id": "deity_defense__crb_",
    "name": {
      "value": "Defense"
    },
    "source": {
      "value": "unknown"
    },
    "category": {
      "value": "deity"
    },
    "prerequisites_text": {
      "value": ""
    },
    "description": {
      "value": "> Defense Associated Domain: Protection. Replacement Power: The following granted power replaces the resistant touch power of the Protection domain. Deflection Aura (Su): Once each day, you can emit a 20- foot aura for a number of rounds equal to your cleric level. Allies within the aura gain a +2 deflection bonus to AC and combat maneuver defense. Replacement Domain Spells: 1st\u00e2\u0080\u0094 shield, 2nd\u00e2\u0080\u0094 barkskin, 7th\u00e2\u0080\u0094 deflection."
    },
    "related_mechanical_resource_id": {
      "value": ""
    }
  }
}