{
  "resource_id": "feat",
  "stats": {
    "id": "feat_tower_shield_proficiency_combat__crb_",
    "name": {
      "value": "Tower Shield Proficiency"
    },
    "source": {
      "value": "unknown"
    },
    "type": {
      "value": "style"
    },
    "traits": {
      "value": "style"
    },
    "prerequisites": {
      "value": "Shield Proficiency."
    },
    "description": {
      "value": "**Benefit:** When you use a tower shield, the shield\u2019s armor check penalty only applies to Strength and Dexterity-based skills.\n\n**Normal:** A character using a shield with which he is not proficient takes the shield\u2019s armor check penalty on attack rolls and on all skill checks that involve moving, including Ride.\n\n**Special:** Fighters automatically have Tower Shield Proficiency as a bonus feat. They need not select it."
    },
    "action_cost": {
      "value": "passive"
    },
    "is_toggleable": {
      "value": false
    },
    "effects": {
      "value": []
    }
  }
}