{
  "resource_id": "feat",
  "stats": {
    "id": "feat_dragonfly_flight_combat__crb_",
    "name": {
      "value": "Dragonfly Flight"
    },
    "source": {
      "value": "martial_arts_handbook"
    },
    "type": {
      "value": "style"
    },
    "traits": {
      "value": "style"
    },
    "prerequisites": {
      "value": "Dex 15, Wis 15, Dragonfly Style, Dragonfly Wings, Improved Unarmed Strike, Acrobatics 10 ranks, Climb 10 ranks."
    },
    "description": {
      "value": "**Benefit:** While using Dragonfly Style, you can attempt an Acrobatics check to high jump as a move action, and then immediately glide as the spell for 1 round. If you have not used your standard action after using Dragonfly Flight to make a high jump and start gliding, you can charge while gliding. This charge follows the rules for charging when you are only able to take a standard action."
    },
    "action_cost": {
      "value": "passive"
    },
    "is_toggleable": {
      "value": false
    },
    "effects": {
      "value": []
    }
  }
}