{
  "resource_id": "feat",
  "stats": {
    "id": "feat_robust_stench__crb_",
    "name": {
      "value": "Robust Stench"
    },
    "source": {
      "value": "heroes_of_golarion"
    },
    "type": {
      "value": "general"
    },
    "traits": {
      "value": "general"
    },
    "prerequisites": {
      "value": "Goblin."
    },
    "description": {
      "value": "**Benefit:** Allies within 5 feet of you receive a +2 morale bonus on Fortitude saving throws. This bonus ends as soon as they move more than 5 feet away from you. This bonus applies only to allies you have fought alongside at least once before."
    },
    "action_cost": {
      "value": "passive"
    },
    "is_toggleable": {
      "value": false
    },
    "effects": {
      "value": []
    }
  }
}