{
  "resource_id": "feat",
  "stats": {
    "id": "feat_beast_hunter_combat__crb_",
    "name": {
      "value": "Beast Hunter"
    },
    "source": {
      "value": "pathfinder_roleplaying_game_ultimate_wilderness"
    },
    "type": {
      "value": "combat"
    },
    "traits": {
      "value": "combat"
    },
    "prerequisites": {
      "value": "Base attack bonus +1; Knowledge (nature) or Survival 1 rank."
    },
    "description": {
      "value": "**Benefit:** Pick one of the ranger\u2019s favored terrains. You gain a +2 bonus on Survival checks to track animals native to that terrain. Additionally, against animals native to that terrain that are at least one size category larger than you, you gain a +1 dodge bonus to your AC and a +1 insight bonus on attack rolls.\n\n**Special:** You can take this feat multiple times. Each time you select this feat, you can choose an additional favored terrain to gain the listed benefits in."
    },
    "action_cost": {
      "value": "passive"
    },
    "is_toggleable": {
      "value": false
    },
    "effects": {
      "value": []
    }
  }
}