{
  "resource_id": "feat",
  "stats": {
    "id": "feat_impressive_grit_weapon_mastery__crb_",
    "name": {
      "value": "Impressive Grit (Weapon Mastery)"
    },
    "source": {
      "value": "weapon_master_s_handbook"
    },
    "type": {
      "value": "combat"
    },
    "traits": {
      "value": "combat"
    },
    "prerequisites": {
      "value": "Base attack bonus +11, weapon training class feature with a ranged weapon."
    },
    "description": {
      "value": "**Benefit:** Select one of the following gunslinger deeds: dead shot, startling shot, or targeting. You can perform the selected deed a number of times per day equal to your highest mental ability score modifier ( Intelligence, Wisdom, or Charisma; minimum 1). You can use this deed with an appropriate ranged weapon. If you also have the selected deed as a class feature, reduce the number of grit points that you need to use it by 1, as per the Signature Deed feat.\n\n**Special:** You can select Impressive Grit up to three times. Each time you select it, choose a different gunslinger deed. A gunslinger can ignore the weapon training class feature prerequisite of Impressive Grit."
    },
    "action_cost": {
      "value": "passive"
    },
    "is_toggleable": {
      "value": false
    },
    "effects": {
      "value": []
    }
  }
}