{
  "resource_id": "feat",
  "stats": {
    "id": "feat_eldritch_claws__crb_",
    "name": {
      "value": "Eldritch Claws"
    },
    "source": {
      "value": "unknown"
    },
    "type": {
      "value": "combat"
    },
    "traits": {
      "value": "combat"
    },
    "prerequisites": {
      "value": "Str 15, natural weapons, base attack bonus +6."
    },
    "description": {
      "value": "**Benefit:** Your natural weapons are considered both magic and silver for purpose of overcoming damage reduction."
    },
    "action_cost": {
      "value": "passive"
    },
    "is_toggleable": {
      "value": false
    },
    "effects": {
      "value": []
    }
  }
}