{
  "resource_id": "feat",
  "stats": {
    "id": "feat_improved_initiative_combat__crb_",
    "name": {
      "value": "Improved Initiative"
    },
    "source": {
      "value": "unknown"
    },
    "type": {
      "value": "combat"
    },
    "traits": {
      "value": "combat"
    },
    "prerequisites": {
      "value": ""
    },
    "description": {
      "value": "**Benefit:** You get a +4 bonus on initiative checks."
    },
    "action_cost": {
      "value": "passive"
    },
    "is_toggleable": {
      "value": false
    },
    "effects": {
      "value": []
    }
  }
}