{
  "resource_id": "feat",
  "stats": {
    "id": "feat_vigilant_phantom__crb_",
    "name": {
      "value": "Vigilant Phantom"
    },
    "source": {
      "value": "pathfinder_roleplaying_game_occult_adventures"
    },
    "type": {
      "value": "general"
    },
    "traits": {
      "value": "general"
    },
    "prerequisites": {
      "value": "Phantom class feature."
    },
    "description": {
      "value": "**Benefit:** While your phantom is within your reach, you gain a +4 bonus on Perception checks. If you have 10 or more ranks in Perception, this bonus increases to +8. This doesn\u2019t apply if your phantom is helpless or unconscious."
    },
    "action_cost": {
      "value": "passive"
    },
    "is_toggleable": {
      "value": false
    },
    "effects": {
      "value": []
    }
  }
}