{
  "resource_id": "feat",
  "stats": {
    "id": "feat_craft_wondrous_item_item_creation__crb_",
    "name": {
      "value": "Craft Wondrous Item"
    },
    "source": {
      "value": "unknown"
    },
    "type": {
      "value": "item_creation"
    },
    "traits": {
      "value": "item_creation"
    },
    "prerequisites": {
      "value": "Caster level 3rd."
    },
    "description": {
      "value": "**Benefit:** You can create a wide variety of magic wondrous items. Crafting a wondrous item takes 1 day for each 1,000 gp in its price. To create a wondrous item, you must use up raw materials costing half of its base price. You can also mend a broken wondrous item if it is one that you could make. Doing so costs half the raw materials and half the time it would take to craft that item. See magic item creation rules for more information."
    },
    "action_cost": {
      "value": "passive"
    },
    "is_toggleable": {
      "value": false
    },
    "effects": {
      "value": []
    }
  }
}