{
  "resource_id": "feat",
  "stats": {
    "id": "feat_improved_monster_lore__crb_",
    "name": {
      "value": "Monster Lore, Improved"
    },
    "source": {
      "value": "um"
    },
    "type": {
      "value": "general"
    },
    "traits": {
      "value": "general"
    },
    "prerequisites": {
      "value": "Monster lore class feature."
    },
    "description": {
      "value": "**Benefit:** You gain a sacred bonus on all skill checks to identify the abilities and weaknesses of creatures equal to 1/2 your level in classes that grant you the monster lore class feature."
    },
    "action_cost": {
      "value": "passive"
    },
    "is_toggleable": {
      "value": false
    },
    "effects": {
      "value": []
    }
  }
}