{
  "resource_id": "feat",
  "stats": {
    "id": "feat_improved_mounted_archery__crb_",
    "name": {
      "value": "Improved Mounted Archery"
    },
    "source": {
      "value": "pathfinder_roleplaying_game_adventurers_guide"
    },
    "type": {
      "value": "general"
    },
    "traits": {
      "value": "general"
    },
    "prerequisites": {
      "value": "Mounted Archery, Mounted Combat, Ride 1 rank."
    },
    "description": {
      "value": "**Benefit:** You take no penalty when using a ranged weapon while mounted and taking a double move action. The penalty while your mount is running is reduced to -2."
    },
    "action_cost": {
      "value": "passive"
    },
    "is_toggleable": {
      "value": false
    },
    "effects": {
      "value": []
    }
  }
}