{
  "resource_id": "item",
  "stats": {
    "id": "talisman_necrotic__crb_",
    "name": {
      "value": "Talisman, Necrotic"
    },
    "source": {
      "value": "unknown"
    },
    "type": {
      "value": "adventuring_gear"
    },
    "description": {
      "value": ""
    },
    "cost": {
      "value": {
        "resource_id": "cost",
        "stats": {
          "id": "cost_talisman_necrotic",
          "value": {
            "value": 500
          },
          "unit": {
            "value": "gold"
          }
        }
      }
    },
    "weight": {
      "value": {
        "resource_id": "weight",
        "stats": {
          "id": "wt_talisman_necrotic",
          "value": {
            "value": 1
          },
          "unit": {
            "value": "pounds"
          }
        }
      }
    }
  }
}