{
  "resource_id": "item",
  "stats": {
    "id": "wandering_punishment__crb_",
    "name": {
      "value": "Wandering Punishment"
    },
    "source": {
      "value": "martial_arts_handbook"
    },
    "type": {
      "value": "weapon"
    },
    "is_magic": {
      "value": true
    },
    "description": {
      "value": "Price 30,320 gp; Slot none; CL 15th; Weight 10 lbs.; Aura strong transmutation DESCRIPTION These +3 tetsubos are given to loyal human servants, who use them to enforce the oni\u00e2\u0080\u0099s will. The wielder of a wandering punishment can, as a standard action, assume the appearance of an oni of her size as though under the effects of alter self. This transformation does not affect her ability scores and lasts as long as the weapon is held in one or both hands. Once per day, the wielder can also grow in stature as per enlarge person, taking on the form of a larger oni in the process. This growth lasts 10 minutes or until the wielder drops the wandering punishment. Once per day while enlarged, the wielder can deliver an awesome blow. As a standard action, the wielder can attempt a free bull rush combat maneuver check as part of a standard attack with a wandering punishment. She can\u00e2\u0080\u0099t move with her target if this combat maneuver succeeds. CONSTRUCTION REQUIREMENTS Cost 15,160 gp; Feats Craft Magic Arms and Armor; Spells giant form I"
    },
    "cost": {
      "value": {
        "resource_id": "cost",
        "stats": {
          "id": "cost_wandering_punishment",
          "value": {
            "value": 30320
          },
          "unit": {
            "value": "gold"
          }
        }
      }
    },
    "weight": {
      "value": {
        "resource_id": "weight",
        "stats": {
          "id": "wt_wandering_punishment",
          "value": {
            "value": 10
          },
          "unit": {
            "value": "pounds"
          }
        }
      }
    }
  }
}