{
  "resource_id": "item",
  "stats": {
    "id": "staff_of_healing__crb_",
    "name": {
      "value": "Staff of healing"
    },
    "source": {
      "value": "unknown"
    },
    "type": {
      "value": "staff"
    },
    "is_magic": {
      "value": true
    },
    "description": {
      "value": "Aura moderate conjuration; CL 8th; Slot none; Price 29,600 gp; Weight 5 lbs. DESCRIPTION This white ash staff is decorated with inlaid silver runes. It allows use of the following spells: Cure serious wounds (1 charge) Lesser restoration (1 charge) Remove blindness/deafness (2 charges) Remove disease (3 charges) CONSTRUCTION REQUIREMENTS Craft Staff, cure serious wounds, lesser restoration, remove blindness/deafness, remove disease; Cost 14,800 gp."
    },
    "cost": {
      "value": {
        "resource_id": "cost",
        "stats": {
          "id": "cost_staff_of_healing",
          "value": {
            "value": 29600
          },
          "unit": {
            "value": "gold"
          }
        }
      }
    },
    "weight": {
      "value": {
        "resource_id": "weight",
        "stats": {
          "id": "wt_staff_of_healing",
          "value": {
            "value": 5
          },
          "unit": {
            "value": "pounds"
          }
        }
      }
    }
  }
}