{
  "resource_id": "spell",
  "stats": {
    "id": "speak_with_soul__crb_",
    "name": {
      "value": "Speak with Soul"
    },
    "source": {
      "value": "pathfinder_roleplaying_game_planar_adventures"
    },
    "level": {
      "value": "spell_level_4"
    },
    "school": {
      "value": "necromancy"
    },
    "classes": {
      "value": [
        "antipaladin",
        "cleric",
        "medium",
        "oracle",
        "paladin",
        "shaman",
        "spiritualist"
      ]
    },
    "casting_time": {
      "value": "1 minute"
    },
    "components": {
      "value": "V, S, M (a drop of candle wax)"
    },
    "range": {
      "value": "10 ft."
    },
    "area": {
      "value": "see text"
    },
    "duration": {
      "value": "1 minute/level (D)"
    },
    "saving_throw": {
      "value": "Will negates; see text"
    },
    "spell_resistance": {
      "value": "no"
    },
    "description": {
      "value": "You commune with the soul of a dead creature. To cast this spell, you must be at the soul\u00e2\u0080\u0099s place of death or be in the soul\u00e2\u0080\u0099s presence, whether it is contained in a receptacle, powers an intelligent magic item, or other possibilities. The soul can attempt a Will save to resist the spell as if it were alive. A soul contacted this way can speak normally in any language it knows. Unlike speak with dead and similar spells, you are not limited to asking questions and can engage in normal conversation with the soul (and vice versa). The soul isn\u00e2\u0080\u0099t an undead creature and isn\u00e2\u0080\u0099t compelled to speak or be truthful. Generally, the soul only knows what it knew in life, although souls that persisted with awareness of their surroundings after death may have more to offer. Section 15: Copyright Notice Pathfinder Roleplaying Game Planar Adventures \u00c2\u00a9 2018, Paizo Inc.; Authors: Robert Brookes, John Compton, Paris Crenshaw, Eleanor Ferron, Thurston Hillman, James Jacobs, Isabelle Lee, Lyz Liddell, Ron Lundeen, Joe Pasini, Lacy Pellazar, Jessica Price, Mark Seifter, F. Wesley Schneider, Todd Stewart, James L. Sutter, and Linda Zayas-Palmer."
    }
  }
}