{
  "resource_id": "spell",
  "stats": {
    "id": "burst_bonds__crb_",
    "name": {
      "value": "Burst Bonds"
    },
    "source": {
      "value": "unknown"
    },
    "level": {
      "value": "spell_level_1"
    },
    "school": {
      "value": "evocation"
    },
    "classes": {
      "value": [
        "inquisitor"
      ]
    },
    "casting_time": {
      "value": "1 standard action"
    },
    "components": {
      "value": "V"
    },
    "range": {
      "value": "touch"
    },
    "area": {
      "value": "one object or creature restraining you"
    },
    "duration": {
      "value": "instantaneous"
    },
    "saving_throw": {
      "value": "Fortitude half (object)"
    },
    "spell_resistance": {
      "value": "yes"
    },
    "description": {
      "value": "You blast your restraints with divine wrath, dealing 1d6 points of damage per caster level to the target object (maximum 5d6), ignoring hardness of 10 or less. A Fortitude save halves the damage, although only magical restraints receive a Saving Throw. You can also target a creature that is grappling or otherwise restraining you (such as by adhesive or the swallow whole ability) with the spell. You don\u2019t need to make a touch attack to use burst bonds against a creature, and you can cast this spell without making a concentration check while grappled or pinned. The creature does not take damage as above. If you are grappled and your target fails its save, you may make an immediate attempt to break the grapple (but not reverse it) as a free action, with a +1 luck bonus to your CMB per caster level (maximum +5). If the target creature fails its save and you are restrained by an ability that originally allowed a Saving Throw, burst bonds allows a new Saving Throw with a +1 luck bonus per two caster levels (maximum +5). Section 15: Copyright Notice Advanced Player\u2019s Guide. Copyright 2010, Paizo Publishing, LLC; Author: Jason Bulmahn."
    }
  }
}