{
  "resource_id": "spell",
  "stats": {
    "id": "obscured_script__crb_",
    "name": {
      "value": "Obscured Script"
    },
    "source": {
      "value": "pathfinder_roleplaying_game_adventurers_guide"
    },
    "level": {
      "value": "spell_level_2"
    },
    "school": {
      "value": "illusion"
    },
    "classes": {
      "value": [
        "bard",
        "sorcerer",
        "wizard"
      ]
    },
    "casting_time": {
      "value": "1 standard action"
    },
    "components": {
      "value": "V, S, M (a scrap of paper bearing a simple sentence written in at least five languages)"
    },
    "range": {
      "value": "touch"
    },
    "area": {
      "value": "one touched page, scroll , inscription, book, or other document no more than 3 feet in any dimension"
    },
    "duration": {
      "value": "24 hours (D)"
    },
    "saving_throw": {
      "value": "none; see text"
    },
    "spell_resistance": {
      "value": "no"
    },
    "description": {
      "value": "You create a latent illusion that clouds the judgment and reading ability of any creature that examines a targeted text. While casting the spell, you can designate up to one creature other than yourself per level to be immune to the effects. All other creatures that read the text must succeed at a Will save or find it difficult to properly parse and decipher the contents. This increases the DC of Linguistics checks to decipher the text by an amount equal to your caster level (maximum +10), and it increases the DC of the Wisdom check to avoid drawing a false conclusion by an equal amount. Unaffected creatures gain a circumstance bonus equal to your caster level (maximum +10) on Bluff checks to deceive affected creatures about the text\u2019s contents. The spell obscures any magical glyphs, runes, or symbols within the text, increasing the Perception DC to find such traps by an amount equal to half your caster level (maximum +5). Obscured script can be made permanent with a permanency spell by a caster of 10th level or higher for the cost of 5,000 gp. Section 15: Copyright Notice Pathfinder Roleplaying Game Adventurer\u2019s Guide \u00c2\u00a9 2017, Paizo Inc.; Authors: Benjamin Bruck, John Compton, Crystal Frasier, Tim Hitchcock, Jenny Jarzabski, Isabelle Lee, Joe Pasini, Jessica Price, David Schwartz, and Josh Vogt."
    }
  }
}