{
  "resource_id": "trait",
  "stats": {
    "id": "winter_s_soul_regional_irrisen__crb_",
    "name": {
      "value": "Winter\u00e2\u0080\u0099s Soul"
    },
    "source": {
      "value": "crb"
    },
    "trait_category": {
      "value": "regional"
    },
    "prerequisites": {
      "value": ""
    },
    "description": {
      "value": "**Benefit:** You may cast ray of frost once per day as a spell-like ability. This is cast at your highest caster level gained; if you have no caster level, it functions at CL 1st."
    },
    "is_basic": {
      "value": false
    }
  }
}