{
  "resource_id": "trait",
  "stats": {
    "id": "sense_of_order__crb_",
    "name": {
      "value": "Sense of Order"
    },
    "source": {
      "value": "unknown"
    },
    "trait_category": {
      "value": "religion"
    },
    "prerequisites": {
      "value": ""
    },
    "description": {
      "value": "**Benefit:** You gain a +3 trait bonus on any Perception check made to identify any changes to a location that have occurred since you last visited it."
    },
    "is_basic": {
      "value": false
    }
  }
}